MANIFEST.in
setup.py
pylognorm/__init__.py
pylognorm.egg-info/PKG-INFO
pylognorm.egg-info/SOURCES.txt
pylognorm.egg-info/dependency_links.txt
pylognorm.egg-info/not-zip-safe
pylognorm.egg-info/requires.txt
pylognorm.egg-info/top_level.txt
pylognorm/bindings/__init__.py
pylognorm/bindings/liblognorm.c
tools/cython-modules
tools/dev-requires
tools/install-requires
tools/test-requires